pynetlink/__init__.py
pynetlink/const.py
pynetlink/exceptions.py
pynetlink/models/__init__.py
pynetlink/models/browser.py
pynetlink/models/desk.py
pynetlink/models/discovery.py
pynetlink/models/display.py
pynetlink/models/system.py
pynetlink/netlink.py
pynetlink/py.typed
pynetlink/rest.py
pynetlink/websocket.py
pynetlink-1.1.0.dist-info/METADATA
pynetlink-1.1.0.dist-info/WHEEL
pynetlink-1.1.0.dist-info/licenses/LICENSE
pynetlink-1.1.0.dist-info/RECORD
