Metadata-Version: 2.4
Name: pynetlink
Version: 1.1.0
Summary: Async Python client for Netlink desk and display control
License-Expression: LGPL-3.0-or-later
License-File: LICENSE
Keywords: pynetlink,netlink,desk,display,home-assistant,iot,api,async,client
Author: Klaas Schoute
Author-email: <k.schoute@net-os.com>
Maintainer: Klaas Schoute
Maintainer-email: <k.schoute@net-os.com>
Requires-Python: >=3.12
Classifier: Framework :: AsyncIO
Classifier: Intended Audience :: Developers
Classifier: License :: OSI Approved :: GNU Lesser General Public License v3 or later (LGPLv3+)
Classifier: Natural Language :: English
Classifier: Programming Language :: Python :: 3.12
Classifier: Programming Language :: Python :: 3.13
Classifier: Programming Language :: Python :: 3.14
Classifier: Programming Language :: Python :: 3
Classifier: Topic :: Software Development :: Libraries :: Python Modules
Requires-Dist: aiohttp (>=3.13.0)
Requires-Dist: mashumaro (>=3.17)
Requires-Dist: python-socketio (>=5.15.0)
Requires-Dist: yarl (>=1.22.0)
Requires-Dist: zeroconf (>=0.148.0)
Project-URL: Bug Tracker, https://github.com/MrGreenBoutiqueOffices/python-netlink/issues
Project-URL: Changelog, https://github.com/MrGreenBoutiqueOffices/python-netlink/releases
Project-URL: Documentation, https://github.com/MrGreenBoutiqueOffices/python-netlink
Project-URL: Homepage, https://github.com/MrGreenBoutiqueOffices/python-netlink
Project-URL: Repository, https://github.com/MrGreenBoutiqueOffices/python-netlink
